aioshumway/__init__.py
tests/__init__.py
tests/unit/__init__.py
tests/unit/test_aioshumway.py
aioshumway-1.0.1.dist-info/LICENSE
aioshumway-1.0.1.dist-info/METADATA
aioshumway-1.0.1.dist-info/WHEEL
aioshumway-1.0.1.dist-info/top_level.txt
aioshumway-1.0.1.dist-info/RECORD
