Metadata-Version: 2.1
Name: aioshumway
Version: 1.0.1
Summary: Asynchronous metrics library for ffwd; DEPRECATED
Home-page: https://github.com/spotify/aioshumway
Author: Matt Obarzanek
Author-email: matto@spotify.com
Maintainer: Matt Obarzanek
Maintainer-email: matto@spotify.com
License: Apache 2.0
Keywords: metrics,ffwd,heroic,asyncio
Platform: UNKNOWN
Classifier: Development Status :: 5 - Production/Stable
Classifier: License :: OSI Approved :: Apache Software License
Classifier: Natural Language :: English
Classifier: Operating System :: POSIX :: Linux
Classifier: Operating System :: MacOS :: MacOS X
Classifier: Programming Language :: Python
Classifier: Programming Language :: Python :: 3
Classifier: Programming Language :: Python :: 3.6
Classifier: Programming Language :: Python :: Implementation :: CPython
Classifier: Topic :: Software Development :: Libraries :: Python Modules
License-File: LICENSE
Requires-Dist: shumway (==1.0.0)
